pygora/__init__.py
pygora_phchcc-0.0.14.dist-info/LICENCE
pygora_phchcc-0.0.14.dist-info/METADATA
pygora_phchcc-0.0.14.dist-info/WHEEL
pygora_phchcc-0.0.14.dist-info/top_level.txt
pygora_phchcc-0.0.14.dist-info/RECORD
