Metadata-Version: 2.1
Name: pygora-phchcc
Version: 0.0.14
Summary: A web crawler library that fetches and parses data from Boston College Agora Portal
Home-page: https://github.com/haochenpan/pygora
Author: Haochen Pan
Author-email: phchcc@gmail.com
License: UNKNOWN
Platform: UNKNOWN
Classifier: Programming Language :: Python :: 3
Classifier: License :: OSI Approved :: MIT License
Classifier: Operating System :: OS Independent
Requires-Dist: lxml
Requires-Dist: requests
